pixelyodi/__init__.py
pixelyodi/main.py
yodinew-0.3.2.dist-info/LICENSE
yodinew-0.3.2.dist-info/METADATA
yodinew-0.3.2.dist-info/WHEEL
yodinew-0.3.2.dist-info/top_level.txt
yodinew-0.3.2.dist-info/RECORD
