Metadata-Version: 2.1
Name: yodinew
Version: 0.3.2
License-File: LICENSE
